setup.py
src/pyfnc/__init__.py
src/pyfnc/dic.py
src/pyfnc/fnc.py
src/pyfnc/fnc_tools.py
src/pyfnc/liste.py
src/pyfnc.egg-info/PKG-INFO
src/pyfnc.egg-info/SOURCES.txt
src/pyfnc.egg-info/dependency_links.txt
src/pyfnc.egg-info/not-zip-safe
src/pyfnc.egg-info/top_level.txt
src/pyfnc/examples/__init__.py
src/pyfnc/examples/ex1.py
src/pyfnc/tests/__init__.py
src/pyfnc/tests/test.py
src/pyfnc/tests/test2.py
src/pyfnc/tests/test3.py
src/pyfnc/tests/test4.py
src/pyfnc/tests/test_dic.py
src/pyfnc/tests/test_liste.py