Metadata-Version: 1.0
Name: pyfnc
Version: 0.1.2
Summary: Functional style dictionary and list classes + decorators for pattern matching function dispatch
Home-page: http://www.systemical.com/doc/opensource/pyfnc
Author: Jean-Lou Dupont
Author-email: jl@jldupont.com
License: UNKNOWN
Platform: UNKNOWN
